LICENSE
MANIFEST.in
README.rst
setup.py
bugzilla/__init__.py
bugzilla/agents.py
bugzilla/fields.py
bugzilla/models.py
bugzilla/utils.py
bztools.egg-info/PKG-INFO
bztools.egg-info/SOURCES.txt
bztools.egg-info/dependency_links.txt
bztools.egg-info/entry_points.txt
bztools.egg-info/not-zip-safe
bztools.egg-info/requires.txt
bztools.egg-info/top_level.txt
scripts/__init__.py
scripts/attach.py
scripts/email_nag.py
scripts/phonebook.py
scripts/query_creator.py