Metadata-Version: 1.0
Name: bztools
Version: 0.0.2
Summary: Models and scripts to access the Bugzilla REST API.
Home-page: http://github.com/mozilla/bztools
Author: Jeff Balogh
Author-email: me@jeffbalogh.org
License: BSD
Platform: UNKNOWN
Classifier: Development Status :: 4 - Beta
Classifier: Intended Audience :: Developers
Classifier: License :: OSI Approved :: BSD License
Classifier: Operating System :: OS Independent
Classifier: Programming Language :: Python
Classifier: Topic :: Software Development :: Libraries :: Python Modules
